cli2gui/__init__.py
cli2gui/application/__init__.py
cli2gui/application/application.py
cli2gui/application/application2args.py
cli2gui/decorators.py
cli2gui/gui/__init__.py
cli2gui/gui/abstract_gui.py
cli2gui/gui/dearpygui_wrapper.py
cli2gui/gui/FiraCode-Regular.ttf
cli2gui/gui/helpers.py
cli2gui/gui/pysimplegui_wrapper.py
cli2gui/tojson/__init__.py
cli2gui/tojson/argparse2json.py
cli2gui/tojson/click2json.py
cli2gui/tojson/docopt2json.py
cli2gui/tojson/getopt2json.py
cli2gui/tojson/optparse2json.py
cli2gui/types.py
cli2gui-2024.3.dist-info/LICENSE.md
cli2gui-2024.3.dist-info/METADATA
cli2gui-2024.3.dist-info/WHEEL
cli2gui-2024.3.dist-info/RECORD
