Metadata-Version: 2.1
Name: cli2gui
Version: 2024.3
Summary: Use this module to convert a cli program to a gui
Home-page: https://github.com/FHPythonUtils/Cli2Gui
License: MIT
Author: FredHappyface
Requires-Python: >=3.8,<4.0
Classifier: Development Status :: 5 - Production/Stable
Classifier: Environment :: Console
Classifier: Environment :: MacOS X
Classifier: Environment :: Web Environment
Classifier: Environment :: Win32 (MS Windows)
Classifier: Environment :: X11 Applications :: Qt
Classifier: Intended Audience :: Developers
Classifier: Intended Audience :: Education
Classifier: License :: OSI Approved :: MIT License
Classifier: Natural Language :: English
Classifier: Operating System :: OS Independent
Classifier: Programming Language :: Python :: 3
Classifier: Programming Language :: Python :: 3.8
Classifier: Programming Language :: Python :: 3.9
Classifier: Programming Language :: Python :: 3.10
Classifier: Programming Language :: Python :: 3.11
Classifier: Programming Language :: Python :: 3.12
Classifier: Programming Language :: Python :: Implementation :: CPython
Classifier: Topic :: Software Development :: Libraries :: Python Modules
Classifier: Topic :: Utilities
Provides-Extra: fsg
Provides-Extra: pandoc
Provides-Extra: psg
Provides-Extra: qt
Provides-Extra: web
Requires-Dist: Pillow (>=10.2.0,<11)
Requires-Dist: PySimpleGUIQt (>=5.0.0,<6) ; extra == "qt"
Requires-Dist: PySimpleGUIWeb (>=0.39.0,<2) ; extra == "web"
Requires-Dist: PyYAML (>=6.0.1,<7)
Requires-Dist: catpandoc (>=2024,<2026) ; extra == "pandoc"
Requires-Dist: dearpygui (>=1.11.1,<2)
Requires-Dist: freesimplegui (>=5.1.1,<6) ; extra == "fsg"
Requires-Dist: getostheme (>=2024.0.1,<2026)
Requires-Dist: pysimplegui (>=5.0.3,<6) ; extra == "psg"
Project-URL: Documentation, https://github.com/FHPythonUtils/Cli2Gui/blob/master/README.md
Project-URL: Repository, https://github.com/FHPythonUtils/Cli2Gui
